examples/__init__.py
lhorizon/__init__.py
lhorizon/_request_formatters.py
lhorizon/_response_parsers.py
lhorizon/_type_aliases.py
lhorizon/base.py
lhorizon/config.py
lhorizon/constants.py
lhorizon/handlers.py
lhorizon/lhorizon_utils.py
lhorizon/solutions.py
lhorizon/target.py
lhorizon/targeter_utils.py
lhorizon/kernels/__init__.py
lhorizon/kernels/de440s.bsp
lhorizon/kernels/earth_latest_high_prec.bpc
lhorizon/kernels/lhorizon_metakernel.tm
lhorizon/kernels/load.py
lhorizon/kernels/moon_080317.tf
lhorizon/kernels/moon_pa_de421_1900-2050.bpc
lhorizon/kernels/naif0012.tls
lhorizon/kernels/pck00011.tpc
lhorizon/tests/data/CERES_2000_OBSERVER_df.csv
lhorizon/tests/data/CERES_2000_OBSERVER_table.csv
lhorizon/tests/data/CERES_2000_VECTORS_df.csv
lhorizon/tests/data/CERES_2000_VECTORS_table.csv
lhorizon/tests/data/CYDONIA_PALM_SPRINGS_1959_TOPO_OBSERVER_df.csv
lhorizon/tests/data/CYDONIA_PALM_SPRINGS_1959_TOPO_OBSERVER_table.csv
lhorizon/tests/data/CYDONIA_PALM_SPRINGS_1959_TOPO_VECTORS_df.csv
lhorizon/tests/data/CYDONIA_PALM_SPRINGS_1959_TOPO_VECTORS_table.csv
lhorizon/tests/data/MARS_SUN_ANGLE_MINIMAL.csv
lhorizon/tests/data/MEUDON_MOON_NOW_OBSERVER_df.csv
lhorizon/tests/data/MEUDON_MOON_NOW_OBSERVER_table.csv
lhorizon/tests/data/MEUDON_MOON_NOW_VECTORS_df.csv
lhorizon/tests/data/MEUDON_MOON_NOW_VECTORS_table.csv
lhorizon/tests/data/SUN_PHOBOS_1999_OBSERVER_df.csv
lhorizon/tests/data/SUN_PHOBOS_1999_OBSERVER_table.csv
lhorizon/tests/data/SUN_PHOBOS_1999_VECTORS_df.csv
lhorizon/tests/data/SUN_PHOBOS_1999_VECTORS_table.csv
lhorizon/tests/data/TRANQUILITY_2021_CENTER.csv
lhorizon/tests/data/TRANQUILITY_2021_TARGET.csv
lhorizon/tests/data/WEIRD_OPTIONS_OBSERVER_df.csv
lhorizon/tests/data/WEIRD_OPTIONS_OBSERVER_table.csv
lhorizon/tests/data/WEIRD_OPTIONS_VECTORS_df.csv
lhorizon/tests/data/WEIRD_OPTIONS_VECTORS_table.csv
lhorizon/tests/data/__init__.py
lhorizon/tests/data/test_cases.py
lhorizon/vendor/__init__.py
lhorizon/vendor/telnetlib.py
lhorizon-1.1.10.dist-info/licenses/LICENSE
lhorizon-1.1.10.dist-info/METADATA
lhorizon-1.1.10.dist-info/WHEEL
lhorizon-1.1.10.dist-info/top_level.txt
lhorizon-1.1.10.dist-info/RECORD
