Metadata-Version: 2.4
Name: lhorizon
Version: 1.1.10
Summary: lhorizon helps you find things in the solar system
Home-page: https://github.com/millionconcepts/lhorizon.git
Author: Million Concepts
Author-email: mstclair@millionconcepts.com
Requires-Python: >=3.11
License-File: LICENSE
Requires-Dist: numpy
Requires-Dist: more-itertools
Requires-Dist: requests
Requires-Dist: pandas
Requires-Dist: pyerfa
Provides-Extra: tests
Requires-Dist: pytest; extra == "tests"
Requires-Dist: pytest-mock; extra == "tests"
Requires-Dist: pytest-cov; extra == "tests"
Provides-Extra: target
Requires-Dist: spiceypy; extra == "target"
Requires-Dist: sympy; extra == "target"
Provides-Extra: examples
Requires-Dist: jupyter; extra == "examples"
Provides-Extra: benchmarks
Requires-Dist: memory-profiler; extra == "benchmarks"
Requires-Dist: pympler; extra == "benchmarks"
Requires-Dist: astroquery; extra == "benchmarks"
Dynamic: author
Dynamic: author-email
Dynamic: description
Dynamic: home-page
Dynamic: license-file
Dynamic: provides-extra
Dynamic: requires-dist
Dynamic: requires-python
Dynamic: summary
